README.rst
setup.py
secudata/__init__.py
secudata/secu_data.py
secudata.egg-info/PKG-INFO
secudata.egg-info/SOURCES.txt
secudata.egg-info/dependency_links.txt
secudata.egg-info/top_level.txt